qc/__init__.py
qc/anomaly.py
qc/demographicsGraphs.py
qc/extract.py
qc/labMeasurementsAnomalies.py
qc/labMeasurementsGraphs.py
qc/missingDataImputation.py
qc/pipeline.py
qc/utils.py
qc/vitalsAnomalies.py
qc/vitalsGraphs.py
test/__init__.py
test/context.py
test/dbUtils.py
test/test.py
EHRQC-0.4.dist-info/LICENSE
EHRQC-0.4.dist-info/METADATA
EHRQC-0.4.dist-info/WHEEL
EHRQC-0.4.dist-info/top_level.txt
EHRQC-0.4.dist-info/RECORD
