Metadata-Version: 2.1
Name: EHRQC
Version: 0.4
Summary: Package for performing QC on Electronic Health Record (EHR) data
Home-page: https://github.com/ryashpal/EHRQC
Author: Yashpal Ramakrishnaiah <ryashpal.ramakrishnaiah1@monash.edu>, Sonika Tyagi <sonika.tyagi@monash.edu>
Author-email: ryashpal.ramakrishnaiah1@monash.edu, sonika.tyagi@monash.edu
License: MIT
Platform: UNKNOWN
Classifier: Programming Language :: Python :: 3
Classifier: License :: OSI Approved :: MIT License
Classifier: Operating System :: OS Independent
Classifier: Operating System :: OS Independent
Classifier: Intended Audience :: Science/Research
Classifier: Intended Audience :: Healthcare Industry
Requires-Python: >=3.6
